hserve/__init__.py
hserve/server.py
hserve-0.1.0.dist-info/METADATA
hserve-0.1.0.dist-info/WHEEL
hserve-0.1.0.dist-info/entry_points.txt
hserve-0.1.0.dist-info/RECORD
